actionsMCP/__init__.py
actionsMCP/entry_point.cpython-310-x86_64-linux-gnu.so
actionsMCP/petitions/__init__.py
actionsMCP/petitions/get_hash.cpython-310-x86_64-linux-gnu.so
actionsMCP/petitions/get_land.cpython-310-x86_64-linux-gnu.so
actionsMCP/petitions/get_packs.cpython-310-x86_64-linux-gnu.so
actionsMCP/petitions/get_resources.cpython-310-x86_64-linux-gnu.so
actionsMCP/petitions/get_sign.cpython-310-x86_64-linux-gnu.so
actionsMCP/petitions/get_signature.cpython-310-x86_64-linux-gnu.so
actionsMCP/petitions/send_tx.cpython-310-x86_64-linux-gnu.so
actionsMCP-1.4.1.dist-info/LICENSE
actionsMCP-1.4.1.dist-info/METADATA
actionsMCP-1.4.1.dist-info/WHEEL
actionsMCP-1.4.1.dist-info/top_level.txt
actionsMCP-1.4.1.dist-info/RECORD
