Metadata-Version: 2.1
Name: actionsMCP
Version: 1.4.1
Summary: This package provides the necessary parameters to perform actions on MCP
Author: brunodev12
Author-email: bruno.carter.dev@gmail.com
Classifier: License :: Other/Proprietary License
Classifier: Programming Language :: Python :: 3.10
Classifier: Operating System :: POSIX :: Linux
License-File: LICENSE
Requires-Dist: websocket-client ==1.4.1
